skquantreg/__init__.py
skquantreg/quantreg.py
skquantreg-0.0.5.dist-info/DESCRIPTION.rst
skquantreg-0.0.5.dist-info/METADATA
skquantreg-0.0.5.dist-info/RECORD
skquantreg-0.0.5.dist-info/WHEEL
skquantreg-0.0.5.dist-info/metadata.json
skquantreg-0.0.5.dist-info/top_level.txt
