Metadata-Version: 2.0
Name: skquantreg
Version: 0.0.5
Summary: Scikit wrapper for quantreg
Home-page: https://github.com/Marco-Santoni/skquantreg
Author: Marco Santoni
Author-email: marcosantoni@hotmail.it
License: BSD
Download-URL: https://github.com/Marco-Santoni/skquantreg/tarball/0.0.5
Platform: UNKNOWN
Classifier: Development Status :: 3 - Alpha
Classifier: Intended Audience :: Developers
Classifier: Programming Language :: Python :: 3
Requires-Dist: nose
Requires-Dist: coverage
Requires-Dist: twine
Requires-Dist: scikit-learn
Requires-Dist: statsmodels
Requires-Dist: scipy
